bemused/__init__.py
bemused/bem.py
bemused/fast_interpolation.py
bemused/models.py
bemused-0.2.0.dist-info/AUTHORS.rst
bemused-0.2.0.dist-info/LICENSE.txt
bemused-0.2.0.dist-info/METADATA
bemused-0.2.0.dist-info/WHEEL
bemused-0.2.0.dist-info/top_level.txt
bemused-0.2.0.dist-info/RECORD
