Metadata-Version: 2.1
Name: bemused
Version: 0.2.0
Summary: Blade Element Momentum calculations
Home-page: https://github.com/ricklupton/bemused
Author: Rick Lupton
Author-email: mail@ricklupton.name
License: mit
Platform: any
Classifier: Development Status :: 4 - Beta
Classifier: Programming Language :: Python
Requires-Dist: numpy
Requires-Dist: scipy (>=0.19)
Requires-Dist: pyyaml
Provides-Extra: testing
Requires-Dist: pytest ; extra == 'testing'
Requires-Dist: pytest-cov ; extra == 'testing'
Requires-Dist: pandas ; extra == 'testing'
